setup.py
dbx_unittest2pytest/__init__.py
dbx_unittest2pytest/main.py
dbx_unittest2pytest.egg-info/PKG-INFO
dbx_unittest2pytest.egg-info/SOURCES.txt
dbx_unittest2pytest.egg-info/dependency_links.txt
dbx_unittest2pytest.egg-info/entry_points.txt
dbx_unittest2pytest.egg-info/not-zip-safe
dbx_unittest2pytest.egg-info/top_level.txt
dbx_unittest2pytest/fixes/__init__.py
dbx_unittest2pytest/fixes/fix_asserts.py