Metadata-Version: 1.0
Name: dbx-unittest2pytest
Version: 1.0
Summary: Convert unittest asserts to pytest rewritten asserts
Home-page: https://github.com/dropbox/dbx-unittest2pytest
Author: Nipunn Koorapati, David Euresti
Author-email: nipunn@dropbox.com, david@dropbox.com
License: Apache License 2.0
Keywords: unittest pytest dropbox
Platform: UNKNOWN
